ferc_xbrl_extractor/__init__.py
ferc_xbrl_extractor/_version.py
ferc_xbrl_extractor/arelle_interface.py
ferc_xbrl_extractor/cli.py
ferc_xbrl_extractor/datapackage.py
ferc_xbrl_extractor/helpers.py
ferc_xbrl_extractor/instance.py
ferc_xbrl_extractor/taxonomy.py
ferc_xbrl_extractor/xbrl.py
catalystcoop_ferc_xbrl_extractor-1.8.0.dist-info/METADATA
catalystcoop_ferc_xbrl_extractor-1.8.0.dist-info/WHEEL
catalystcoop_ferc_xbrl_extractor-1.8.0.dist-info/entry_points.txt
catalystcoop_ferc_xbrl_extractor-1.8.0.dist-info/licenses/LICENSE.txt
catalystcoop_ferc_xbrl_extractor-1.8.0.dist-info/RECORD
