Metadata-Version: 2.4
Name: catalystcoop.ferc_xbrl_extractor
Version: 1.8.0
Summary: A tool for extracting data from FERC XBRL Filings.
Project-URL: Homepage, https://github.com/catalyst-cooperative/ferc-xbrl-extractor
Project-URL: Source, https://github.com/catalyst-cooperative/ferc-xbrl-extractor
Project-URL: Documentation, https://catalystcoop-ferc-xbrl-extractor.readthedocs.io
Project-URL: Issue Tracker, https://github.com/catalyst-cooperative/ferc-xbrl-extractor/issues
Author-email: Catalyst Cooperative <pudl@catalyst.coop>, Zach Schira <zach.schira@catalyst.coop>
License: MIT License
License-File: LICENSE.txt
Keywords: accounting,data,electricity,energy,federal energy regulatory commission,ferc,finance,gas,natural gas,oil,regulation,utility,xbrl
Classifier: Development Status :: 5 - Production/Stable
Classifier: Environment :: Console
Classifier: License :: OSI Approved :: MIT License
Classifier: Natural Language :: English
Classifier: Operating System :: OS Independent
Classifier: Programming Language :: Python
Classifier: Programming Language :: Python :: 3
Classifier: Programming Language :: Python :: 3 :: Only
Classifier: Programming Language :: Python :: 3.11
Classifier: Programming Language :: Python :: 3.12
Classifier: Programming Language :: Python :: 3.13
Classifier: Programming Language :: Python :: 3.14
Requires-Python: <3.15.0a0,>=3.11
Requires-Dist: arelle-release>=2.32
Requires-Dist: coloredlogs>=14.0
Requires-Dist: duckdb>=1.3.2
Requires-Dist: frictionless<6,>=5
Requires-Dist: lxml>=4.9.1
Requires-Dist: numpy<3,>=1.16
Requires-Dist: pandas>=1.5
Requires-Dist: pyarrow>=14.0.1
Requires-Dist: pydantic<3,>=2
Requires-Dist: sqlalchemy<3,>=1.4
Requires-Dist: stringcase>=1.2
Provides-Extra: dev
Requires-Dist: hatch>=1.16; extra == 'dev'
Requires-Dist: ruff>=0.14; extra == 'dev'
Provides-Extra: docs
Requires-Dist: doc8>=2; extra == 'docs'
Requires-Dist: furo>=2024; extra == 'docs'
Requires-Dist: sphinx-autoapi>=3; extra == 'docs'
Requires-Dist: sphinx-issues>=5; extra == 'docs'
Requires-Dist: sphinx>=9; extra == 'docs'
Provides-Extra: tests
Requires-Dist: coverage>=7; extra == 'tests'
Requires-Dist: doc8>=2; extra == 'tests'
Requires-Dist: mypy>=1; extra == 'tests'
Requires-Dist: pre-commit>=4; extra == 'tests'
Requires-Dist: pydocstyle>=6; extra == 'tests'
Requires-Dist: pytest-console-scripts>=1; extra == 'tests'
Requires-Dist: pytest-cov>=7; extra == 'tests'
Requires-Dist: pytest-mock>=3; extra == 'tests'
Requires-Dist: pytest>=9; extra == 'tests'
Requires-Dist: ruff>=0.14; extra == 'tests'
Provides-Extra: types
Requires-Dist: types-setuptools; extra == 'types'
